B_HIT/__init__.py
B_HIT/.ipynb_checkpoints/__init__-checkpoint.py
B_HIT/sVDJ/__init__.py
B_HIT/sVDJ/pl/richness_boxplot.py
B_HIT/sVDJ/tl/__init__.py
B_HIT/sVDJ/tl/compute_correlation.py
B_HIT/sVDJ/tl/compute_grouped_index.py
B_HIT/sVDJ/tl/spatial_bcr_desc.py
B_HIT/sVDJ/tl/summarize_BCR.py
B_HIT/st/__init__.py
B_HIT/st/gr/__init__.py
B_HIT/st/gr/_aggr.py
B_HIT/st/gr/_get_adj.py
B_HIT/st/pl/__init__.py
B_HIT/st/pl/_clustering_results.py
B_HIT/st/pl/_enrichment_score.py
B_HIT/st/pl/_kde_results.py
B_HIT/st/pl/_silhouette_score.py
B_HIT/st/tl/_GMM.py
B_HIT/st/tl/__init__.py
B_HIT/st/tl/_cluster_Auto_k.py
B_HIT/st/tl/_dbscan_filter.py
B_HIT/st/tl/_kde_filter.py
b_hit-0.4.2.dist-info/METADATA
b_hit-0.4.2.dist-info/WHEEL
b_hit-0.4.2.dist-info/licenses/LICENSE
b_hit-0.4.2.dist-info/RECORD
