Metadata-Version: 2.4
Name: B_HIT
Version: 0.4.2
Summary: A Python package for the identification, characterization and comparison of spatial clusters from spatial -omics data.
Author: Zeng lab
Maintainer-email: yuanrh2004 <yuanrh2004@gmail.com>
License: Copyright (c) 2018 The Python Packaging Authority
License-File: LICENSE
Requires-Python: <3.12,>=3.8
Requires-Dist: anndata<0.11.0
Requires-Dist: matplotlib<3.9.0
Requires-Dist: pytorch-lightning>=1.6.0
Requires-Dist: scikit-learn
Requires-Dist: spatialdata
Requires-Dist: spatialdata-plot>=0.1.0
Requires-Dist: squidpy
Requires-Dist: torchgmm
Requires-Dist: tqdm
Provides-Extra: dev
Requires-Dist: pre-commit; extra == 'dev'
Requires-Dist: twine; extra == 'dev'
Provides-Extra: doc
Requires-Dist: docutils!=0.18.*,!=0.19.*,>=0.8; extra == 'doc'
Requires-Dist: ipykernel>=6.0.0; extra == 'doc'
Requires-Dist: ipython>=7.0.0; extra == 'doc'
Requires-Dist: myst-nb>=1.1.0; extra == 'doc'
Requires-Dist: sphinx-autodoc-typehints>=1.0.0; extra == 'doc'
Requires-Dist: sphinx-book-theme>=1.0.0; extra == 'doc'
Requires-Dist: sphinx-copybutton>=0.3.0; extra == 'doc'
Requires-Dist: sphinx-design; extra == 'doc'
Requires-Dist: sphinx>=4.0.0; extra == 'doc'
Requires-Dist: sphinxcontrib-bibtex>=1.0.0; extra == 'doc'
Provides-Extra: proteomics
Requires-Dist: scarches; extra == 'proteomics'
Provides-Extra: test
Requires-Dist: pytest; extra == 'test'
Requires-Dist: pytest-cov; extra == 'test'
Provides-Extra: transcriptomics
Requires-Dist: scvi-tools; extra == 'transcriptomics'
